my_sdk/api.cp313-win_amd64.pyd
my_sdk/core.cp313-win_amd64.pyd
harry_test_sdk_mamotion-0.0.8.dist-info/METADATA
harry_test_sdk_mamotion-0.0.8.dist-info/WHEEL
harry_test_sdk_mamotion-0.0.8.dist-info/top_level.txt
harry_test_sdk_mamotion-0.0.8.dist-info/RECORD
